tompy/__init__.py
tompy/any.py
tompy/dataframe.py
tompy/io.py
tompy/main.py
tompy/matrix.py
tompy/py.typed
tompy/scalar.py
tompy/series.py
tompy/vector.py
tompy-1.0.0.dist-info/LICENSE
tompy-1.0.0.dist-info/WHEEL
tompy-1.0.0.dist-info/METADATA
tompy-1.0.0.dist-info/RECORD
